artemis_utils/__init__.py
artemis_utils/conf_lib.py
artemis_utils/constants.py
artemis_utils/db.py
artemis_utils/envvars.py
artemis_utils/logaux.py
artemis_utils/rabbitmq.py
artemis_utils/redis.py
artemis_utils/rpki.py
artemis_utils/service.py
artemis_utils/translations.py
artemis_utils/updates.py
artemis_utils-1.0.16.1.dist-info/LICENSE.txt
artemis_utils-1.0.16.1.dist-info/METADATA
artemis_utils-1.0.16.1.dist-info/WHEEL
artemis_utils-1.0.16.1.dist-info/top_level.txt
artemis_utils-1.0.16.1.dist-info/RECORD
