Metadata-Version: 2.1
Name: artemis-utils
Version: 1.0.16.1
Summary: ARTEMIS utility modules
Home-page: https://github.com/FORTH-ICS-INSPIRE/artemis
Author: Dimitrios Mavrommatis, Vassileios Kotronis
Author-email: jim.mavrommatis@gmail.com, biece89@gmail.com
License: UNKNOWN
Platform: UNKNOWN
Classifier: Programming Language :: Python :: 3
Classifier: License :: OSI Approved :: MIT License
Classifier: Operating System :: OS Independent
Requires-Python: >=3.6
License-File: LICENSE.txt
Requires-Dist: kombu (==4.6.3)
Requires-Dist: ruamel.yaml (==0.16.5)
Requires-Dist: ujson (==1.35)
Requires-Dist: PyYAML (==5.4)
Requires-Dist: gql (==0.4.0)
Requires-Dist: ipaddress (==1.0.23)
Requires-Dist: psycopg2 (==2.8.4)
Requires-Dist: slacker-log-handler (==1.7.1)
Requires-Dist: tornado (==6.0.4)
